.gitignore
ChangeLog.rst
MANIFEST.in
README.rst
VERSION
make.sh
setup.py
setup.py.in
bin/ramdisk
doc/manpage.rst
doc/manpage.rst.in
doc/ramdisk.8
funtoo_ramdisk/__init__.py
funtoo_ramdisk/args.py
funtoo_ramdisk/config_files.py
funtoo_ramdisk/const.py
funtoo_ramdisk/initramfs.py
funtoo_ramdisk/kernel.py
funtoo_ramdisk/log.py
funtoo_ramdisk/modules.py
funtoo_ramdisk/plugin_base.py
funtoo_ramdisk/utilities.py
funtoo_ramdisk/version.py
funtoo_ramdisk.egg-info/PKG-INFO
funtoo_ramdisk.egg-info/SOURCES.txt
funtoo_ramdisk.egg-info/dependency_links.txt
funtoo_ramdisk.egg-info/requires.txt
funtoo_ramdisk.egg-info/top_level.txt
funtoo_ramdisk/plugins/__init__.py
funtoo_ramdisk/plugins/btrfs.py
funtoo_ramdisk/plugins/core.py
funtoo_ramdisk/plugins/luks.py
funtoo_ramdisk/plugins/lvm.py
funtoo_ramdisk/support/__init__.py
funtoo_ramdisk/support/initramfs.cpio
funtoo_ramdisk/support/linuxrc
funtoo_ramdisk/support/etc/initrd.defaults
funtoo_ramdisk/support/etc/initrd.scripts
funtoo_ramdisk/support/etc/plugins/__init__.py
funtoo_ramdisk/support/etc/plugins/scan_mode/__init__.py
funtoo_ramdisk/support/etc/plugins/scan_mode/legacy.sh
funtoo_ramdisk/support/etc/plugins/scan_mode/udev.sh
funtoo_ramdisk/support/module_configs/__init__.py
funtoo_ramdisk/support/module_configs/full/__init__.py
funtoo_ramdisk/support/module_configs/full/modules.autoload
funtoo_ramdisk/support/module_configs/full/modules.copy