Metadata-Version: 2.1
Name: funtoo-ramdisk
Version: 1.1.17
Summary: Funtoo framework for creating initial ramdisks.
Home-page: https://code.funtoo.org/bitbucket/users/drobbins/repos/funtoo-ramdisk/browse
Author: Daniel Robbins, Funtoo Solutions Inc.
Author-email: drobbins@funtoo.org
Classifier: Programming Language :: Python :: 3
Classifier: License :: OSI Approved :: Apache Software License
Classifier: Operating System :: POSIX :: Linux
Requires-Python: >=3.7
Requires-Dist: rich
